rpi_metar.py
rpi_metar-0.1.0.dist-info/DESCRIPTION.rst
rpi_metar-0.1.0.dist-info/METADATA
rpi_metar-0.1.0.dist-info/RECORD
rpi_metar-0.1.0.dist-info/WHEEL
rpi_metar-0.1.0.dist-info/entry_points.txt
rpi_metar-0.1.0.dist-info/metadata.json
rpi_metar-0.1.0.dist-info/top_level.txt
