Metadata-Version: 2.0
Name: rpi-metar
Version: 0.1.0
Summary: Visualizing METAR data on a Raspberry Pi with LEDs.
Home-page: https://github.com/ScottSturdivant/rpi_metar
Author: Scott Sturdivant
Author-email: scott.sturdivant@gmail.com
License: MIT
Keywords: METAR,Raspberry Pi
Platform: UNKNOWN
Classifier: Development Status :: 4 - Beta
Classifier: License :: OSI Approved :: MIT License
Classifier: Programming Language :: Python :: 3
Requires-Python: >=3
Requires-Dist: requests (==2.18.4)
Requires-Dist: retrying (==1.3.3)
Requires-Dist: rpi-ws281x (==3.0.3)
